mpy_topsis/pro1.py
mpy_topsis-1.0.3.dist-info/LICENSE
mpy_topsis-1.0.3.dist-info/METADATA
mpy_topsis-1.0.3.dist-info/WHEEL
mpy_topsis-1.0.3.dist-info/entry_points.txt
mpy_topsis-1.0.3.dist-info/top_level.txt
mpy_topsis-1.0.3.dist-info/RECORD
