Metadata-Version: 2.1
Name: mpy-topsis
Version: 1.0.3
Summary: Technique for Order Preference by Similarity to Ideal Solution.
Home-page: https://github.com/manikmangla9
Author: manik mangla
Author-email: manikmangla9@gmail.com
License: MIT
Platform: UNKNOWN
Classifier: License :: OSI Approved :: MIT License
Classifier: Programming Language :: Python :: 3
Classifier: Programming Language :: Python :: 3.7
Classifier: Programming Language :: Python :: 2.7
Requires-Dist: pandas
Requires-Dist: numpy
